src/__init__.py
src/extendables/__init__.py
src/extendables/get_data.py
src/extendables/get_prediction_lambda.py
src/extendables/get_predictions.py
src/generate_values/__init__.py
src/generate_values/generate_counterfactuals_binary.py
src/generate_values/generate_counterfactuals_multiclass.py
src/generate_values/generate_counterfactuals_regression.py
src/generate_values/generate_drift_score_counterfactual_binary.py
src/generate_values/generate_drift_score_counterfactual_multiclass.py
src/generate_values/generate_drift_score_counterfactual_regression.py
src/generate_values/generate_fairness_binary.py
src/generate_values/generate_fairness_multiclass.py
src/generate_values/generate_fairness_regression.py
src/generate_values/generate_performance_values_binary.py
src/generate_values/generate_performance_values_multiclass.py
src/generate_values/generate_performance_values_regression.py
src/generate_values/generate_predictions_live.py
src/utils/__init__.py
src/utils/counterfactual_common_functions.py
src/utils/get_connections.py
src/utils/get_data_generic.py
src/utils/performance_common_functions.py
src/utils/shap_common_functions.py
complai_test-0.1.dist-info/METADATA
complai_test-0.1.dist-info/WHEEL
complai_test-0.1.dist-info/RECORD
