Metadata-Version: 2.1
Name: complai-test
Version: 0.1
Summary: test version
Author: Your Name
Author-email: you@example.com
Requires-Python: >=3.8,<3.9
Classifier: Programming Language :: Python :: 3
Classifier: Programming Language :: Python :: 3.8
Requires-Dist: dask[distributed] (==2.3.0)
Requires-Dist: fsspec (==2022.3.0)
Requires-Dist: nicex (==0.1.0)
Requires-Dist: numpy (==1.21.2)
Requires-Dist: pandas (==1.3.2)
Requires-Dist: protobuf (==3.19.4)
Requires-Dist: scikit-learn (==0.22)
Requires-Dist: tensorflow (==2.2.0)
Requires-Dist: tinydb (==4.4.0)
